{"id":195,"page":"best","name":"Kingdom (2019)","description":"\\n                        Orphaned by war, a young boy and his friend dream of changing their fate and becoming the world's greatest generals. And after his friend sacrifices himself to protect the future emperor, the young boy's path to greatness is set in motion. Helping the King reclaim the throne puts the boy's blade to the ultimate test as they go against deadly assassins, large armies, and the dangerous mountain clan. In a country torn apart by war, only they can fight to unite the warring states! Kingdom is a live-action motion picture based on the bestselling adventure-historical manga series of the same name created by Yasuhisa Hara and presents a fictionalized account of ancient China during the Warring States Period (475-221 BC).\\n                    ","ratings":[{"critic":"RT critics","rating":"The best"},{"critic":"RT audience","rating":"Good"},{"critic":"RT audience","rating":"Beyond good"}],"categories":["Action & Adventure","Drama","Action","Horror"],"imageName":"Kingdom (2019)"}